ocebuild/__init__.py
ocebuild/cli/__init__.py
ocebuild/cli/__main__.py
ocebuild/cli/_lib.py
ocebuild/cli/commands/__init__.py
ocebuild/cli/commands/build.py
ocebuild/cli/commands/lock.py
ocebuild/cli/commands/patch.py
ocebuild/cli/console.py
ocebuild/cli/interactive.py
ocebuild/cli/logging.py
ocebuild/constants.py
ocebuild/errors/__init__.py
ocebuild/errors/_lib.py
ocebuild/errors/types.py
ocebuild/errors/validation.py
ocebuild/filesystem/__init__.py
ocebuild/filesystem/archives.py
ocebuild/filesystem/archives_test.py
ocebuild/filesystem/cache.py
ocebuild/filesystem/cache_test.py
ocebuild/filesystem/posix.py
ocebuild/filesystem/posix_test.py
ocebuild/parsers/__init__.py
ocebuild/parsers/_lib.py
ocebuild/parsers/asl.py
ocebuild/parsers/asl_test.py
ocebuild/parsers/dict.py
ocebuild/parsers/dict_test.py
ocebuild/parsers/plist.py
ocebuild/parsers/plist_test.py
ocebuild/parsers/regex.py
ocebuild/parsers/regex_test.py
ocebuild/parsers/schema.py
ocebuild/parsers/schema_test.py
ocebuild/parsers/types.py
ocebuild/parsers/types_test.py
ocebuild/parsers/yaml.py
ocebuild/parsers/yaml_test.py
ocebuild/pipeline/__init__.py
ocebuild/pipeline/build.py
ocebuild/pipeline/build_test.py
ocebuild/pipeline/config.py
ocebuild/pipeline/config_test.py
ocebuild/pipeline/kexts.py
ocebuild/pipeline/kexts_test.py
ocebuild/pipeline/lock.py
ocebuild/pipeline/lock_test.py
ocebuild/pipeline/opencore.py
ocebuild/pipeline/opencore_test.py
ocebuild/pipeline/packages.py
ocebuild/pipeline/packages_test.py
ocebuild/pipeline/ssdts.py
ocebuild/pipeline/ssdts_test.py
ocebuild/sources/__init__.py
ocebuild/sources/_lib.py
ocebuild/sources/binary.py
ocebuild/sources/binary_test.py
ocebuild/sources/dortania.py
ocebuild/sources/dortania_test.py
ocebuild/sources/github.py
ocebuild/sources/github_test.py
ocebuild/sources/resolver.py
ocebuild/sources/resolver_test.py
ocebuild/third_party/__init__.py
ocebuild/third_party/__pycache__/__init__.cpython-312.pyc
ocebuild/third_party/cpython/__init__.py
ocebuild-0.1.1.dev0.dist-info/entry_points.txt
ocebuild-0.1.1.dev0.dist-info/LICENSE
ocebuild-0.1.1.dev0.dist-info/METADATA
ocebuild-0.1.1.dev0.dist-info/WHEEL
ocebuild-0.1.1.dev0.dist-info/RECORD
