Metadata-Version: 2.1
Name: ocebuild
Version: 0.1.1.dev0
Summary: Portable OpenCore EFI dependency & build manager.
Home-page: https://github.com/Qonfused/OCE-Build
License: BSD-3-Clause
Keywords: cli,tui,packaging,dependency,opencore
Author: Cory Bennett
Author-email: csquaredbennett@gmail.com
Requires-Python: >=3.8
Classifier: Development Status :: 2 - Pre-Alpha
Classifier: Environment :: Console
Classifier: Intended Audience :: Developers
Classifier: License :: OSI Approved :: BSD License
Classifier: Operating System :: OS Independent
Classifier: Programming Language :: C++
Classifier: Programming Language :: Python
Classifier: Programming Language :: Python :: 3
Classifier: Programming Language :: Python :: 3.8
Classifier: Programming Language :: Python :: 3.9
Classifier: Programming Language :: Python :: 3.10
Classifier: Programming Language :: Python :: 3.11
Classifier: Programming Language :: Python :: Implementation :: CPython
Classifier: Topic :: Software Development :: Build Tools
Classifier: Topic :: Software Development :: Libraries
Classifier: Topic :: Software Development :: Libraries :: Python Modules
Requires-Dist: graphlib_backport (>=1.0.0,<2.0.0) ; python_version < "3.9"
Requires-Dist: packaging (>=23.0,<24.0)
Requires-Dist: python-dotenv (>=1.0.0,<2.0.0)
Requires-Dist: typing_extensions (>=4.2.0,<5.0.0) ; python_version < "3.10"
Project-URL: Documentation, https://ocebuild.readthedocs.io/
Project-URL: Repository, https://github.com/Qonfused/OCE-Build
